server.py
mseep_bluesky_social_mcp-0.1.1.dist-info/licenses/LICENSE
mseep_bluesky_social_mcp-0.1.1.dist-info/METADATA
mseep_bluesky_social_mcp-0.1.1.dist-info/WHEEL
mseep_bluesky_social_mcp-0.1.1.dist-info/entry_points.txt
mseep_bluesky_social_mcp-0.1.1.dist-info/top_level.txt
mseep_bluesky_social_mcp-0.1.1.dist-info/RECORD
