Metadata-Version: 2.4
Name: mseep-bluesky-social-mcp
Version: 0.1.1
Summary: Add your description here
Author-email: mseep <support@skydeck.ai>
Requires-Python: >=3.12
License-File: LICENSE
Requires-Dist: atproto>=0.0.61
Requires-Dist: mcp[cli]>=1.9.0
Requires-Dist: pytest>=8.3.5
Requires-Dist: pytest-asyncio>=0.26.0
Requires-Dist: requests>=2.32.3
Requires-Dist: trio>=0.30.0
Dynamic: license-file
